puzzlepiece/__init__.py
puzzlepiece/_snippets.py
puzzlepiece/action.py
puzzlepiece/icon.png
puzzlepiece/param.py
puzzlepiece/parse.py
puzzlepiece/piece.py
puzzlepiece/puzzle.py
puzzlepiece/readout.py
puzzlepiece/threads.py
puzzlepiece/extras/__init__.py
puzzlepiece/extras/datagrid.py
puzzlepiece/extras/hardware_tools.py
puzzlepiece/extras/ipython_shims.py
puzzlepiece/pieces/__init__.py
puzzlepiece/pieces/param_setter.py
puzzlepiece/pieces/plotter.py
puzzlepiece/pieces/random_number.py
puzzlepiece/pieces/scan.py
puzzlepiece/pieces/scan_value.py
puzzlepiece/pieces/script.py
puzzlepiece-1.0.1.dist-info/METADATA
puzzlepiece-1.0.1.dist-info/WHEEL
puzzlepiece-1.0.1.dist-info/licenses/LICENSE
puzzlepiece-1.0.1.dist-info/RECORD
