Metadata-Version: 2.4
Name: puzzlepiece
Version: 1.0.1
Summary: A GUI-forward Python framework for automating experimental setups.
Project-URL: Homepage, https://github.com/jdranczewski/puzzlepiece
Project-URL: Documentation, https://puzzlepiece.readthedocs.io
Project-URL: Bug Tracker, https://github.com/jdranczewski/puzzlepiece/issues
Author-email: Jakub Dranczewski <jakub.dranczewski@gmail.com>
License-File: LICENSE
Classifier: Development Status :: 3 - Alpha
Classifier: License :: OSI Approved :: Apache Software License
Classifier: Operating System :: OS Independent
Classifier: Programming Language :: Python :: 3
Requires-Python: >=3.7
Requires-Dist: numpy
Requires-Dist: pyqtgraph
Requires-Dist: qtpy
